rocketchat_bot_app_bridge/BotBackendController.py
rocketchat_bot_app_bridge/RCBot.py
rocketchat_bot_app_bridge/__init__.py
rocketchat_bot_app_bridge/definitions/__init__.py
rocketchat_bot_app_bridge/definitions/application.py
rocketchat_bot_app_bridge/definitions/message.py
rocketchat_bot_app_bridge/definitions/room.py
rocketchat_bot_app_bridge/definitions/user.py
rocketchat_bot_simple_app_bot-0.1.0.dist-info/LICENSE
rocketchat_bot_simple_app_bot-0.1.0.dist-info/METADATA
rocketchat_bot_simple_app_bot-0.1.0.dist-info/WHEEL
rocketchat_bot_simple_app_bot-0.1.0.dist-info/top_level.txt
rocketchat_bot_simple_app_bot-0.1.0.dist-info/RECORD
