Metadata-Version: 2.1
Name: rocketchat-bot-simple-app-bot
Version: 0.1.0
Summary: Bot client for rocketchat BotBridgeApp
Home-page: https://github.com/JargeZ/RocketChat-Simple-AppBot
Author: Pavel Khorikov
Author-email: lev@ph3.ru
License: UNKNOWN
Platform: UNKNOWN
Classifier: Programming Language :: Python :: 3
Classifier: License :: OSI Approved :: MIT License
Classifier: Operating System :: OS Independent
Requires-Python: >=3.8
Requires-Dist: Webhook-Listener
Requires-Dist: loguru
